talkit_agent/__init__.py
talkit_agent/ai_agents.py
talkit_agent/ai_models.py
talkit_agent/ai_tools.py
talkit_agent/chat.py
talkit_agent/context.py
talkit_agent/open_api.py
talkit_agent/talkit_agent.py
talkit_agent/tools/tool_get_action.py
talkit_agent-0.1.3.dist-info/licenses/LICENSE
talkit_agent-0.1.3.dist-info/METADATA
talkit_agent-0.1.3.dist-info/WHEEL
talkit_agent-0.1.3.dist-info/top_level.txt
talkit_agent-0.1.3.dist-info/RECORD
