Metadata-Version: 2.4
Name: talkit-agent
Version: 0.1.3
Summary: Talkit Agent turns any OpenAPI spec into a conversational API assistant. It understands user prompts, picks the right endpoint, makes the call, and returns the result. Just talk to your API.
Project-URL: PiPy, https://pypi.org/project/talkit-agent/
Project-URL: Repository, https://github.com/gilvaneigregorio/talkit_agent/tree/main
Requires-Python: >=3.12
License-File: LICENSE
Requires-Dist: openai-agents>=0.0.14
Requires-Dist: pytest>=8.3.5
Requires-Dist: ruff>=0.11.8
Dynamic: license-file
